myCalculatorPackagezzr/__init__.py
myCalculatorPackagezzr/division/__init__.py
myCalculatorPackagezzr/division/divide.py
myCalculatorPackagezzr/multiplication/__init__.py
myCalculatorPackagezzr/multiplication/multiply.py
myCalculatorPackagezzr-0.0.1.dist-info/LICENSE.txt
myCalculatorPackagezzr-0.0.1.dist-info/METADATA
myCalculatorPackagezzr-0.0.1.dist-info/WHEEL
myCalculatorPackagezzr-0.0.1.dist-info/top_level.txt
myCalculatorPackagezzr-0.0.1.dist-info/RECORD
